pytest_test_grouping/__init__.py
pytest_test_grouping-1.0.3b0.dist-info/LICENSE
pytest_test_grouping-1.0.3b0.dist-info/METADATA
pytest_test_grouping-1.0.3b0.dist-info/WHEEL
pytest_test_grouping-1.0.3b0.dist-info/entry_points.txt
pytest_test_grouping-1.0.3b0.dist-info/top_level.txt
pytest_test_grouping-1.0.3b0.dist-info/RECORD
