Metadata-Version: 2.1
Name: pytest-test-grouping
Version: 1.0.3b0
Summary: A Pytest plugin for running a subset of your tests by splitting them in to equally sized groups.
Home-page: https://github.com/i4ali/pytest-test-grouping.git
Author: Imran Ali
Author-email: ali.muhammadimran@gmail.com
License: UNKNOWN
Platform: UNKNOWN
Classifier: Development Status :: 5 - Production/Stable
Classifier: Intended Audience :: Developers
Classifier: License :: OSI Approved :: MIT License
Classifier: Operating System :: OS Independent
Classifier: Programming Language :: Python
Classifier: Topic :: Software Development :: Testing
Classifier: Programming Language :: Python :: 2.7
Classifier: Programming Language :: Python :: 3.7
Classifier: Programming Language :: Python :: 3.8
License-File: LICENSE
Requires-Dist: pytest (>=2.5)
